flexiformatter/__init__.py
flexiformatter/reformat_flexiplex_tags.py
flexiformatter-1.0.6.dist-info/licenses/LICENSE
flexiformatter-1.0.6.dist-info/METADATA
flexiformatter-1.0.6.dist-info/WHEEL
flexiformatter-1.0.6.dist-info/entry_points.txt
flexiformatter-1.0.6.dist-info/top_level.txt
flexiformatter-1.0.6.dist-info/RECORD
